fastapi_sessions/__init__.py
fastapi_sessions/backends/__init__.py
fastapi_sessions/backends/implementations/__init__.py
fastapi_sessions/backends/implementations/in_memory_backend.py
fastapi_sessions/backends/session_backend.py
fastapi_sessions/frontends/__init__.py
fastapi_sessions/frontends/implementations/__init__.py
fastapi_sessions/frontends/implementations/cookie.py
fastapi_sessions/frontends/session_frontend.py
fastapi_sessions/session_verifier.py
fastapi_sessions-0.3.1.dist-info/WHEEL
fastapi_sessions-0.3.1.dist-info/METADATA
fastapi_sessions-0.3.1.dist-info/RECORD
