Metadata-Version: 2.1
Name: fastapi-sessions
Version: 0.3.1
Summary: Ready-to-use session library for FastAPI
Home-page: https://github.com/jordanisaacs/fastapi-sessions
License: MIT
Keywords: sessions,cookies,authorization,fastapi
Author: Jordan Isaacs
Requires-Python: >=3.6.1,<4.0
Classifier: Framework :: AsyncIO
Classifier: Intended Audience :: Developers
Classifier: License :: OSI Approved :: MIT License
Classifier: Programming Language :: Python :: 3
Classifier: Programming Language :: Python :: 3 :: Only
Classifier: Programming Language :: Python :: 3.6
Classifier: Programming Language :: Python :: 3.7
Classifier: Programming Language :: Python :: 3.8
Classifier: Programming Language :: Python :: 3.9
Classifier: Topic :: Internet :: WWW/HTTP :: Session
Provides-Extra: dev
Provides-Extra: docs
Requires-Dist: black (>=20.8b1,<21.0); extra == "dev"
Requires-Dist: fastapi (>=0.65,<0.66)
Requires-Dist: flake8 (>=3.9.0,<4.0.0); extra == "dev"
Requires-Dist: flake8-docstrings (>=1.6.0,<2.0.0); extra == "dev"
Requires-Dist: isort (>=5.9.3,<6.0.0); extra == "dev"
Requires-Dist: itsdangerous (>=2.0.1,<3.0.0)
Requires-Dist: markdown-include (>=0.6.0,<0.7.0); extra == "docs"
Requires-Dist: mkdocs-material (>=7.1.0,<8.0.0); extra == "docs"
Requires-Dist: pytest (>=6.2.3,<7.0.0); extra == "dev"
Requires-Dist: uvicorn (>=0.14.0,<0.15.0); extra == "dev"
Project-URL: Documentation, https://jordanisaacs.github.io/fastapi-sessions/
